{
  "UC1hnBY1vAbEVqzxKiXZWv3Q": [
    "KY7DWWvWe3Y",
    "K0ZYXdgAc4c",
    "Hn-JreAj1W0",
    "k2XmOFj0xfU",
    "wXYKaYG6k8Q",
    "zJ81eKtHMuE",
    "fVvvOfeKddU",
    "DAI614Czoik",
    "_VwwIlbQLsg",
    "M75513WIpt0",
    "hZLNO6LTbjU",
    "sPxd2483MDU",
    "g9cQlDqH-cM",
    "vywuFM8sWvo",
    "tHHY6_9fKU0",
    "JtqcZr3dAro",
    "TOf4d43LP48"
  ],
  "UCro1VNb7hqX38TvyUN64JkQ": [
    "Vg5dSTKAUmI",
    "7HLq8_7ZQIQ",
    "yN9MvQIaXCM",
    "2M_e-2iNR3s",
    "IQ9AiT4jPx8",
    "aw35zF_Ra5w",
    "OoTiyuXw_8s",
    "RxSR3WhdWUg",
    "vTKGzhF0_sA",
    "dLbJ9QD3kCs",
    "OeWyzKZeWpg",
    "QCaLBlkqou8",
    "Vi9PAszIsEo",
    "yBh9WquCIa8",
    "WFZCilkK0NQ",
    "vVSx7vtSy3s",
    "WyDHvSBudw0",
    "lYSk-UNQBQA",
    "vtfvWQQ2CLM",
    "bmIPDJa5RGo"
  ],
  "UCSCcv_YI5ZdpbrzK53M3YzQ": [
    "3RwejUiH5_Q",
    "31y8Sqleiw0",
    "SN_JQCPWPw4",
    "Y9tFwT-n084",
    "hxKh36fIB70",
    "tbndge-YNL4",
    "5y8MVQBHdow",
    "4HpHKHtrGK0",
    "Fyf66y7V73Y",
    "3HOVOBm0w-g",
    "A9n8vNkCc6U",
    "kysj8fvXBXo",
    "1E4m9uJWIyI",
    "MdVFlBBI84Q",
    "7uku8R_BLFo",
    "TnqCVIuToVc",
    "Ynb8Zj2bnqc",
    "WQJHuTBnDHM",
    "ZD02rmu2GNQ",
    "NP_ho8r4stI",
    "e5TUPiOIHcw",
    "hSzT9id4Il4",
    "vNbCvtILFew",
    "1SqVtuh0ZLc"
  ],
  "UCXdyP1Nh0Gtix48XVUjNqXQ": [
    "aTK-ZY2HpPI",
    "Bvrmx1maTyo",
    "TXezybJYY8U",
    "-P0g_BPg3Jw",
    "HcXl1XscaTo",
    "MFPR2ab-geE",
    "JsZmmPuarwY",
    "5vvJVixzMh8",
    "hQjvO_9Uveg",
    "Jq14ZDMluU4",
    "lx_1AbEmCxo",
    "8CFNQAn_Wq0",
    "UzQf1bAE9aI",
    "cV_TlpSOEPk",
    "7T0RNcDz9M8",
    "dG5emu7Ruvs",
    "CNTTd5LTa2Q",
    "m50J7c6H93Q",
    "aaWMjRfTadQ",
    "e8JVSm2He6E",
    "kb_WeYMjvAw"
  ],
  "UC6rh4_O86hGLVPdUhwroxtw": [
    "ysEkv2Z7N_Y",
    "nVq3g9A3-NI",
    "Wh6VGjhT2u8",
    "g0sKu4FK8KU",
    "daT6Fq5Mhhk",
    "ryeuJssgyN0",
    "GGLd53kpVvk",
    "88g71fzH_qY",
    "m_-bn5ifMDs",
    "2wXjHrDObNA",
    "gKepHxTSgcw",
    "hYlEdt2W1EY",
    "f9giWXidOxk",
    "Nit11OklDis",
    "h0uM8qpT8ME",
    "nluoKR2Gf9k",
    "PaFx_VHoQ9c",
    "gQ41zilm4lM",
    "EY3k8EtyI3E"
  ]
}